<topSong><!--Copyright (c) 2010 Mark Logic Corporation. Permission is
granted to copy, distribute and/or modify this document under the terms of the
GNU Free Documentation License, Version 1.2 or any later version published by
the Free Software Foundation; with no Invariant Sections, no Front-Cover Texts,
and no Back-Cover Texts. A copy of the license is included in the section 
entitled "GNU Free Documentation License." Content derived from 
http://en.wikipedia.org/wiki/Fly,_Robin,_Fly 

Modified in February 2010 by Mark Logic Corporation under the terms of the 
GNU Free Documentation License.--><songId>http://en.wikipedia.org/wiki/Fly,_Robin,_Fly</songId>
   <title>Fly, Robin, Fly</title>
   <artist>
      <artistId>http://en.wikipedia.org/wiki/Silver_Convention</artistId>
      <artistName>Silver Convention</artistName>
   </artist>
   <weeks>
      <week>1975-11-29</week>
      <week>1975-12-06</week>
      <week>1975-12-13</week>
   </weeks>
   <album>
      <albumImageId>http://upload.wikimedia.org/wikipedia/en/thumb/5/5c/Silver_Convention.jpg/200px-Silver_Convention.jpg</albumImageId>
      <albumImageUri>/images/Silver-Convention+Fly-Robin-Fly.jpg</albumImageUri>
      <albumName>Save Me</albumName>
   </album>
   <released>1975  (1975)</released>
   <formats>
      <format>7"</format>
   </formats>
   <genres>
      <genre>Disco</genre>
   </genres>
   <lengths>
      <length>5:35</length>
   </lengths>
   <descr>
      <p>"Fly, Robin, Fly" is a 1975 song by the German group Silver
    Convention. The song was released as a single from their 1975
    album 
    <i>Save Me</i>. In the United States, it rose to number one on
    the Hot 100 in November 1975, staying there for three weeks.
    The single also stayed at number one on the soul singles chart
    for one week. "Fly, Robin, Fly" also spent three weeks at
    number one on the disco/dance charts. It was the first song by
    a German pop group to reach number one on the American music
    charts.</p>
      <p>"Fly, Robin, Fly" carries the distinction of being a
    Billboard chart-topper with one of the fewest numbers of unique
    words: six. The chorus simply repeats "
    <i>Fly, robin, fly</i>" three times, with an ending of "
    <i>Up, up to the sky!</i>" This was because the singers had
    trouble learning English, and they didn't want to have to learn
    an entire song to sing.</p>
      <p>During the song's segment on VH1's 100 Greatest Dance Songs,
    it was revealed that the song's working title was "Run, Rabbit,
    Run".</p>
      <p>"Fly, Robin, Fly" won a Grammy Award for Best R&amp;B
    Instrumental Performance in 1976.</p>
      <p>American jazz flautist Herbie Mann recorded a version of
    "Fly, Robin, Fly" for his 1976 album, 
    <i>Bird in a Silver Cage,</i>which was co-produced and arranged
    by Sylvester Levay.</p>
      <p>Australian/British string quartet Bond also recorded a
    version of "Fly, Robin, Fly" for their 2004 album, 
    <i>Classified.</i>
      </p>
      <p>In 2003, German lifestyle company Apartment20 produced a
    version of "Fly, Robin, Fly," which featured former Silver
    Convention singer Ramona Wulf on lead vocals and in the video
    for the song.</p>
   </descr>
</topSong>
